jupyter_container/__init__.py
jupyter_container/_version.py
jupyter_container/handlers.py
jupyter_container/tests/__init__.py
jupyter_container/tests/test_handlers.py
jupyter_container-0.0.3.data/data/etc/jupyter/jupyter_notebook_config.d/jupyter_container.json
jupyter_container-0.0.3.data/data/etc/jupyter/jupyter_server_config.d/jupyter_container.json
jupyter_container-0.0.3.data/data/share/jupyter/labextensions/@datalayer/jupyter-container/build_log.json
jupyter_container-0.0.3.data/data/share/jupyter/labextensions/@datalayer/jupyter-container/package.json
jupyter_container-0.0.3.data/data/share/jupyter/labextensions/@datalayer/jupyter-container/schemas/@datalayer/jupyter-container/package.json.orig
jupyter_container-0.0.3.data/data/share/jupyter/labextensions/@datalayer/jupyter-container/schemas/@datalayer/jupyter-container/plugin.json
jupyter_container-0.0.3.data/data/share/jupyter/labextensions/@datalayer/jupyter-container/static/lib_index_js.3817860c83c66e237795.js
jupyter_container-0.0.3.data/data/share/jupyter/labextensions/@datalayer/jupyter-container/static/lib_index_js.3817860c83c66e237795.js.map
jupyter_container-0.0.3.data/data/share/jupyter/labextensions/@datalayer/jupyter-container/static/node_modules_object-assign_index_js.cc5ddd49d5d28f38134e.js
jupyter_container-0.0.3.data/data/share/jupyter/labextensions/@datalayer/jupyter-container/static/node_modules_object-assign_index_js.cc5ddd49d5d28f38134e.js.map
jupyter_container-0.0.3.data/data/share/jupyter/labextensions/@datalayer/jupyter-container/static/remoteEntry.ac5d1b81366777636df1.js
jupyter_container-0.0.3.data/data/share/jupyter/labextensions/@datalayer/jupyter-container/static/remoteEntry.ac5d1b81366777636df1.js.map
jupyter_container-0.0.3.data/data/share/jupyter/labextensions/@datalayer/jupyter-container/static/style.js
jupyter_container-0.0.3.data/data/share/jupyter/labextensions/@datalayer/jupyter-container/static/style_index_js.7a5cbd1252d6ad16c809.js
jupyter_container-0.0.3.dist-info/METADATA
jupyter_container-0.0.3.dist-info/WHEEL
jupyter_container-0.0.3.dist-info/licenses/LICENSE
jupyter_container-0.0.3.dist-info/RECORD
